{
  "fetched_at": "2026-03-27T09:23:00.733973",
  "teams": [
    {
      "abbrev": "COL",
      "name": "Colorado Avalanche",
      "conference": "Western",
      "division": "Central",
      "wins": 48,
      "losses": 13,
      "ot_losses": 10,
      "points": 106,
      "games_played": 71,
      "goal_differential": 87
    },
    {
      "abbrev": "DAL",
      "name": "Dallas Stars",
      "conference": "Western",
      "division": "Central",
      "wins": 43,
      "losses": 18,
      "ot_losses": 11,
      "points": 97,
      "games_played": 72,
      "goal_differential": 47
    },
    {
      "abbrev": "CAR",
      "name": "Carolina Hurricanes",
      "conference": "Eastern",
      "division": "Metropolitan",
      "wins": 45,
      "losses": 20,
      "ot_losses": 6,
      "points": 96,
      "games_played": 71,
      "goal_differential": 41
    },
    {
      "abbrev": "BUF",
      "name": "Buffalo Sabres",
      "conference": "Eastern",
      "division": "Atlantic",
      "wins": 44,
      "losses": 20,
      "ot_losses": 8,
      "points": 96,
      "games_played": 72,
      "goal_differential": 43
    },
    {
      "abbrev": "TBL",
      "name": "Tampa Bay Lightning",
      "conference": "Eastern",
      "division": "Atlantic",
      "wins": 44,
      "losses": 21,
      "ot_losses": 6,
      "points": 94,
      "games_played": 71,
      "goal_differential": 61
    },
    {
      "abbrev": "MIN",
      "name": "Minnesota Wild",
      "conference": "Western",
      "division": "Central",
      "wins": 41,
      "losses": 20,
      "ot_losses": 12,
      "points": 94,
      "games_played": 73,
      "goal_differential": 29
    },
    {
      "abbrev": "MTL",
      "name": "Montr\u00e9al Canadiens",
      "conference": "Eastern",
      "division": "Atlantic",
      "wins": 40,
      "losses": 21,
      "ot_losses": 10,
      "points": 90,
      "games_played": 71,
      "goal_differential": 20
    },
    {
      "abbrev": "BOS",
      "name": "Boston Bruins",
      "conference": "Eastern",
      "division": "Atlantic",
      "wins": 40,
      "losses": 24,
      "ot_losses": 8,
      "points": 88,
      "games_played": 72,
      "goal_differential": 16
    },
    {
      "abbrev": "PIT",
      "name": "Pittsburgh Penguins",
      "conference": "Eastern",
      "division": "Metropolitan",
      "wins": 36,
      "losses": 20,
      "ot_losses": 16,
      "points": 88,
      "games_played": 72,
      "goal_differential": 19
    },
    {
      "abbrev": "CBJ",
      "name": "Columbus Blue Jackets",
      "conference": "Eastern",
      "division": "Metropolitan",
      "wins": 38,
      "losses": 23,
      "ot_losses": 11,
      "points": 87,
      "games_played": 72,
      "goal_differential": 13
    },
    {
      "abbrev": "NYI",
      "name": "New York Islanders",
      "conference": "Eastern",
      "division": "Metropolitan",
      "wins": 41,
      "losses": 27,
      "ot_losses": 5,
      "points": 87,
      "games_played": 73,
      "goal_differential": 4
    },
    {
      "abbrev": "OTT",
      "name": "Ottawa Senators",
      "conference": "Eastern",
      "division": "Atlantic",
      "wins": 38,
      "losses": 24,
      "ot_losses": 10,
      "points": 86,
      "games_played": 72,
      "goal_differential": 22
    },
    {
      "abbrev": "ANA",
      "name": "Anaheim Ducks",
      "conference": "Western",
      "division": "Pacific",
      "wins": 41,
      "losses": 27,
      "ot_losses": 4,
      "points": 86,
      "games_played": 72,
      "goal_differential": -4
    },
    {
      "abbrev": "DET",
      "name": "Detroit Red Wings",
      "conference": "Eastern",
      "division": "Atlantic",
      "wins": 38,
      "losses": 25,
      "ot_losses": 8,
      "points": 84,
      "games_played": 71,
      "goal_differential": -4
    },
    {
      "abbrev": "PHI",
      "name": "Philadelphia Flyers",
      "conference": "Eastern",
      "division": "Metropolitan",
      "wins": 35,
      "losses": 24,
      "ot_losses": 12,
      "points": 82,
      "games_played": 71,
      "goal_differential": -6
    },
    {
      "abbrev": "WSH",
      "name": "Washington Capitals",
      "conference": "Eastern",
      "division": "Metropolitan",
      "wins": 36,
      "losses": 28,
      "ot_losses": 9,
      "points": 81,
      "games_played": 73,
      "goal_differential": 12
    },
    {
      "abbrev": "EDM",
      "name": "Edmonton Oilers",
      "conference": "Western",
      "division": "Pacific",
      "wins": 36,
      "losses": 28,
      "ot_losses": 9,
      "points": 81,
      "games_played": 73,
      "goal_differential": 5
    },
    {
      "abbrev": "UTA",
      "name": "Utah Mammoth",
      "conference": "Western",
      "division": "Central",
      "wins": 37,
      "losses": 30,
      "ot_losses": 6,
      "points": 80,
      "games_played": 73,
      "goal_differential": 19
    },
    {
      "abbrev": "VGK",
      "name": "Vegas Golden Knights",
      "conference": "Western",
      "division": "Pacific",
      "wins": 32,
      "losses": 26,
      "ot_losses": 15,
      "points": 79,
      "games_played": 73,
      "goal_differential": -1
    },
    {
      "abbrev": "NSH",
      "name": "Nashville Predators",
      "conference": "Western",
      "division": "Central",
      "wins": 34,
      "losses": 29,
      "ot_losses": 9,
      "points": 77,
      "games_played": 72,
      "goal_differential": -22
    },
    {
      "abbrev": "NJD",
      "name": "New Jersey Devils",
      "conference": "Eastern",
      "division": "Metropolitan",
      "wins": 37,
      "losses": 32,
      "ot_losses": 2,
      "points": 76,
      "games_played": 71,
      "goal_differential": -18
    },
    {
      "abbrev": "LAK",
      "name": "Los Angeles Kings",
      "conference": "Western",
      "division": "Pacific",
      "wins": 29,
      "losses": 25,
      "ot_losses": 18,
      "points": 76,
      "games_played": 72,
      "goal_differential": -23
    },
    {
      "abbrev": "TOR",
      "name": "Toronto Maple Leafs",
      "conference": "Eastern",
      "division": "Atlantic",
      "wins": 31,
      "losses": 29,
      "ot_losses": 13,
      "points": 75,
      "games_played": 73,
      "goal_differential": -26
    },
    {
      "abbrev": "SEA",
      "name": "Seattle Kraken",
      "conference": "Western",
      "division": "Pacific",
      "wins": 32,
      "losses": 29,
      "ot_losses": 10,
      "points": 74,
      "games_played": 71,
      "goal_differential": -17
    },
    {
      "abbrev": "FLA",
      "name": "Florida Panthers",
      "conference": "Eastern",
      "division": "Atlantic",
      "wins": 35,
      "losses": 33,
      "ot_losses": 3,
      "points": 73,
      "games_played": 71,
      "goal_differential": -23
    },
    {
      "abbrev": "WPG",
      "name": "Winnipeg Jets",
      "conference": "Western",
      "division": "Central",
      "wins": 30,
      "losses": 30,
      "ot_losses": 12,
      "points": 72,
      "games_played": 72,
      "goal_differential": -18
    },
    {
      "abbrev": "SJS",
      "name": "San Jose Sharks",
      "conference": "Western",
      "division": "Pacific",
      "wins": 32,
      "losses": 31,
      "ot_losses": 7,
      "points": 71,
      "games_played": 70,
      "goal_differential": -39
    },
    {
      "abbrev": "STL",
      "name": "St. Louis Blues",
      "conference": "Western",
      "division": "Central",
      "wins": 30,
      "losses": 30,
      "ot_losses": 11,
      "points": 71,
      "games_played": 71,
      "goal_differential": -40
    },
    {
      "abbrev": "CGY",
      "name": "Calgary Flames",
      "conference": "Western",
      "division": "Pacific",
      "wins": 30,
      "losses": 34,
      "ot_losses": 8,
      "points": 68,
      "games_played": 72,
      "goal_differential": -40
    },
    {
      "abbrev": "CHI",
      "name": "Chicago Blackhawks",
      "conference": "Western",
      "division": "Central",
      "wins": 27,
      "losses": 32,
      "ot_losses": 13,
      "points": 67,
      "games_played": 72,
      "goal_differential": -45
    },
    {
      "abbrev": "NYR",
      "name": "New York Rangers",
      "conference": "Eastern",
      "division": "Metropolitan",
      "wins": 28,
      "losses": 35,
      "ot_losses": 9,
      "points": 65,
      "games_played": 72,
      "goal_differential": -28
    },
    {
      "abbrev": "VAN",
      "name": "Vancouver Canucks",
      "conference": "Western",
      "division": "Pacific",
      "wins": 21,
      "losses": 42,
      "ot_losses": 8,
      "points": 50,
      "games_played": 71,
      "goal_differential": -84
    }
  ]
}