{
  "fetched_at": "2026-03-10T07:55:02.735413",
  "teams": [
    {
      "abbrev": "COL",
      "name": "Colorado Avalanche",
      "conference": "Western",
      "division": "Central",
      "wins": 43,
      "losses": 10,
      "ot_losses": 9,
      "points": 95,
      "games_played": 62,
      "goal_differential": 83
    },
    {
      "abbrev": "DAL",
      "name": "Dallas Stars",
      "conference": "Western",
      "division": "Central",
      "wins": 39,
      "losses": 14,
      "ot_losses": 10,
      "points": 88,
      "games_played": 63,
      "goal_differential": 47
    },
    {
      "abbrev": "CAR",
      "name": "Carolina Hurricanes",
      "conference": "Eastern",
      "division": "Metropolitan",
      "wins": 40,
      "losses": 17,
      "ot_losses": 6,
      "points": 86,
      "games_played": 63,
      "goal_differential": 41
    },
    {
      "abbrev": "MIN",
      "name": "Minnesota Wild",
      "conference": "Western",
      "division": "Central",
      "wins": 37,
      "losses": 16,
      "ot_losses": 11,
      "points": 85,
      "games_played": 64,
      "goal_differential": 30
    },
    {
      "abbrev": "BUF",
      "name": "Buffalo Sabres",
      "conference": "Eastern",
      "division": "Atlantic",
      "wins": 39,
      "losses": 19,
      "ot_losses": 6,
      "points": 84,
      "games_played": 64,
      "goal_differential": 32
    },
    {
      "abbrev": "TBL",
      "name": "Tampa Bay Lightning",
      "conference": "Eastern",
      "division": "Atlantic",
      "wins": 39,
      "losses": 19,
      "ot_losses": 4,
      "points": 82,
      "games_played": 62,
      "goal_differential": 51
    },
    {
      "abbrev": "DET",
      "name": "Detroit Red Wings",
      "conference": "Eastern",
      "division": "Atlantic",
      "wins": 36,
      "losses": 21,
      "ot_losses": 7,
      "points": 79,
      "games_played": 64,
      "goal_differential": -1
    },
    {
      "abbrev": "MTL",
      "name": "Montr\u00e9al Canadiens",
      "conference": "Eastern",
      "division": "Atlantic",
      "wins": 34,
      "losses": 18,
      "ot_losses": 10,
      "points": 78,
      "games_played": 62,
      "goal_differential": 13
    },
    {
      "abbrev": "PIT",
      "name": "Pittsburgh Penguins",
      "conference": "Eastern",
      "division": "Metropolitan",
      "wins": 32,
      "losses": 17,
      "ot_losses": 14,
      "points": 78,
      "games_played": 63,
      "goal_differential": 25
    },
    {
      "abbrev": "NYI",
      "name": "New York Islanders",
      "conference": "Eastern",
      "division": "Metropolitan",
      "wins": 36,
      "losses": 23,
      "ot_losses": 5,
      "points": 77,
      "games_played": 64,
      "goal_differential": 5
    },
    {
      "abbrev": "BOS",
      "name": "Boston Bruins",
      "conference": "Eastern",
      "division": "Atlantic",
      "wins": 35,
      "losses": 22,
      "ot_losses": 6,
      "points": 76,
      "games_played": 63,
      "goal_differential": 12
    },
    {
      "abbrev": "CBJ",
      "name": "Columbus Blue Jackets",
      "conference": "Eastern",
      "division": "Metropolitan",
      "wins": 32,
      "losses": 21,
      "ot_losses": 10,
      "points": 74,
      "games_played": 63,
      "goal_differential": 1
    },
    {
      "abbrev": "OTT",
      "name": "Ottawa Senators",
      "conference": "Eastern",
      "division": "Atlantic",
      "wins": 32,
      "losses": 22,
      "ot_losses": 9,
      "points": 73,
      "games_played": 63,
      "goal_differential": 16
    },
    {
      "abbrev": "ANA",
      "name": "Anaheim Ducks",
      "conference": "Western",
      "division": "Pacific",
      "wins": 35,
      "losses": 25,
      "ot_losses": 3,
      "points": 73,
      "games_played": 63,
      "goal_differential": -10
    },
    {
      "abbrev": "UTA",
      "name": "Utah Mammoth",
      "conference": "Western",
      "division": "Central",
      "wins": 34,
      "losses": 25,
      "ot_losses": 5,
      "points": 73,
      "games_played": 64,
      "goal_differential": 27
    },
    {
      "abbrev": "VGK",
      "name": "Vegas Golden Knights",
      "conference": "Western",
      "division": "Pacific",
      "wins": 29,
      "losses": 21,
      "ot_losses": 14,
      "points": 72,
      "games_played": 64,
      "goal_differential": 4
    },
    {
      "abbrev": "WSH",
      "name": "Washington Capitals",
      "conference": "Eastern",
      "division": "Metropolitan",
      "wins": 32,
      "losses": 26,
      "ot_losses": 7,
      "points": 71,
      "games_played": 65,
      "goal_differential": 12
    },
    {
      "abbrev": "EDM",
      "name": "Edmonton Oilers",
      "conference": "Western",
      "division": "Pacific",
      "wins": 31,
      "losses": 25,
      "ot_losses": 8,
      "points": 70,
      "games_played": 64,
      "goal_differential": 9
    },
    {
      "abbrev": "PHI",
      "name": "Philadelphia Flyers",
      "conference": "Eastern",
      "division": "Metropolitan",
      "wins": 29,
      "losses": 23,
      "ot_losses": 11,
      "points": 69,
      "games_played": 63,
      "goal_differential": -17
    },
    {
      "abbrev": "SEA",
      "name": "Seattle Kraken",
      "conference": "Western",
      "division": "Pacific",
      "wins": 29,
      "losses": 24,
      "ot_losses": 9,
      "points": 67,
      "games_played": 62,
      "goal_differential": -9
    },
    {
      "abbrev": "SJS",
      "name": "San Jose Sharks",
      "conference": "Western",
      "division": "Pacific",
      "wins": 30,
      "losses": 25,
      "ot_losses": 6,
      "points": 66,
      "games_played": 61,
      "goal_differential": -23
    },
    {
      "abbrev": "LAK",
      "name": "Los Angeles Kings",
      "conference": "Western",
      "division": "Pacific",
      "wins": 26,
      "losses": 23,
      "ot_losses": 14,
      "points": 66,
      "games_played": 63,
      "goal_differential": -22
    },
    {
      "abbrev": "NJD",
      "name": "New Jersey Devils",
      "conference": "Eastern",
      "division": "Metropolitan",
      "wins": 32,
      "losses": 30,
      "ot_losses": 2,
      "points": 66,
      "games_played": 64,
      "goal_differential": -26
    },
    {
      "abbrev": "FLA",
      "name": "Florida Panthers",
      "conference": "Eastern",
      "division": "Atlantic",
      "wins": 31,
      "losses": 29,
      "ot_losses": 3,
      "points": 65,
      "games_played": 63,
      "goal_differential": -19
    },
    {
      "abbrev": "TOR",
      "name": "Toronto Maple Leafs",
      "conference": "Eastern",
      "division": "Atlantic",
      "wins": 27,
      "losses": 26,
      "ot_losses": 11,
      "points": 65,
      "games_played": 64,
      "goal_differential": -24
    },
    {
      "abbrev": "NSH",
      "name": "Nashville Predators",
      "conference": "Western",
      "division": "Central",
      "wins": 28,
      "losses": 27,
      "ot_losses": 8,
      "points": 64,
      "games_played": 63,
      "goal_differential": -29
    },
    {
      "abbrev": "WPG",
      "name": "Winnipeg Jets",
      "conference": "Western",
      "division": "Central",
      "wins": 26,
      "losses": 26,
      "ot_losses": 10,
      "points": 62,
      "games_played": 62,
      "goal_differential": -11
    },
    {
      "abbrev": "STL",
      "name": "St. Louis Blues",
      "conference": "Western",
      "division": "Central",
      "wins": 25,
      "losses": 29,
      "ot_losses": 9,
      "points": 59,
      "games_played": 63,
      "goal_differential": -46
    },
    {
      "abbrev": "CHI",
      "name": "Chicago Blackhawks",
      "conference": "Western",
      "division": "Central",
      "wins": 24,
      "losses": 29,
      "ot_losses": 11,
      "points": 59,
      "games_played": 64,
      "goal_differential": -35
    },
    {
      "abbrev": "NYR",
      "name": "New York Rangers",
      "conference": "Eastern",
      "division": "Metropolitan",
      "wins": 25,
      "losses": 30,
      "ot_losses": 8,
      "points": 58,
      "games_played": 63,
      "goal_differential": -25
    },
    {
      "abbrev": "CGY",
      "name": "Calgary Flames",
      "conference": "Western",
      "division": "Pacific",
      "wins": 25,
      "losses": 31,
      "ot_losses": 7,
      "points": 57,
      "games_played": 63,
      "goal_differential": -38
    },
    {
      "abbrev": "VAN",
      "name": "Vancouver Canucks",
      "conference": "Western",
      "division": "Pacific",
      "wins": 19,
      "losses": 37,
      "ot_losses": 8,
      "points": 46,
      "games_played": 64,
      "goal_differential": -73
    }
  ]
}